odoo8_addon_hr_emergency_contact-8.0.1.0.0-py2.7-nspkg.pth
odoo_addons/hr_emergency_contact/__openerp__.py
odoo_addons/hr_emergency_contact/__init__.py
odoo_addons/hr_emergency_contact/README.rst
odoo_addons/hr_emergency_contact/models/hr_employee.py
odoo_addons/hr_emergency_contact/models/__init__.py
odoo_addons/hr_emergency_contact/i18n/nl_NL.po
odoo_addons/hr_emergency_contact/i18n/it.po
odoo_addons/hr_emergency_contact/i18n/es.po
odoo_addons/hr_emergency_contact/i18n/ar.po
odoo_addons/hr_emergency_contact/i18n/ro.po
odoo_addons/hr_emergency_contact/i18n/sl.po
odoo_addons/hr_emergency_contact/i18n/de.po
odoo_addons/hr_emergency_contact/i18n/fr.po
odoo_addons/hr_emergency_contact/i18n/pt_BR.po
odoo_addons/hr_emergency_contact/i18n/fi.po
odoo_addons/hr_emergency_contact/views/hr_employee_views.xml
odoo_addons/hr_emergency_contact/static/description/icon.png
odoo8_addon_hr_emergency_contact-8.0.1.0.0.dist-info/top_level.txt
odoo8_addon_hr_emergency_contact-8.0.1.0.0.dist-info/WHEEL
odoo8_addon_hr_emergency_contact-8.0.1.0.0.dist-info/RECORD
odoo8_addon_hr_emergency_contact-8.0.1.0.0.dist-info/metadata.json
odoo8_addon_hr_emergency_contact-8.0.1.0.0.dist-info/DESCRIPTION.rst
odoo8_addon_hr_emergency_contact-8.0.1.0.0.dist-info/METADATA
odoo8_addon_hr_emergency_contact-8.0.1.0.0.dist-info/namespace_packages.txt
